{"asset": {"format": "jpg", "id": "10ba9c65a3beb231ad7aea7a35f5a1a1", "name": "no_face_mask_36.jpg", "path": "file:C:/Users/THINKPAD/Documents/VOTT_image/nomask/image_nomask/no_face_mask_36.jpg", "size": {"width": 1024, "height": 683}, "state": 2, "type": 1}, "regions": [{"id": "je9l9Sxv3", "type": "RECTANGLE", "tags": ["nomask"], "boundingBox": {"height": 154.18896321070235, "width": 138.13154960981046, "left": 372.15607580824974, "top": 165.78882734113714}, "points": [{"x": 372.15607580824974, "y": 165.78882734113714}, {"x": 510.2876254180602, "y": 165.78882734113714}, {"x": 510.2876254180602, "y": 319.97779055183946}, {"x": 372.15607580824974, "y": 319.97779055183946}]}], "version": "2.0.0"}