{"asset": {"format": "jpg", "id": "a5899946ef2c7186a24a1407932fcfdb", "name": "partB328.jpg", "path": "file:C:/Users/THINKPAD/Documents/VOTT_image/B/B/partB328.jpg", "size": {"width": 440, "height": 587}, "state": 2, "type": 1}, "regions": [{"id": "MOPazjXBY", "type": "RECTANGLE", "tags": ["mask"], "boundingBox": {"height": 326.7443365695793, "width": 282.24622030237583, "left": 55.237580993520524, "top": 0}, "points": [{"x": 55.237580993520524, "y": 0}, {"x": 337.48380129589634, "y": 0}, {"x": 337.48380129589634, "y": 326.7443365695793}, {"x": 55.237580993520524, "y": 326.7443365695793}]}], "version": "2.0.0"}